robot_testrail_python2/TestRailAPIClient.py
robot_testrail_python2/TestRailListener.py
robot_testrail_python2/__init__.py
robot_testrail_python2-0.1.dist-info/DESCRIPTION.rst
robot_testrail_python2-0.1.dist-info/METADATA
robot_testrail_python2-0.1.dist-info/RECORD
robot_testrail_python2-0.1.dist-info/WHEEL
robot_testrail_python2-0.1.dist-info/metadata.json
robot_testrail_python2-0.1.dist-info/top_level.txt
